odoo/addons/base_bank_from_iban/README.rst
odoo/addons/base_bank_from_iban/__init__.py
odoo/addons/base_bank_from_iban/__manifest__.py
odoo/addons/base_bank_from_iban/i18n/base_bank_from_iban.pot
odoo/addons/base_bank_from_iban/i18n/de.po
odoo/addons/base_bank_from_iban/i18n/hr.po
odoo/addons/base_bank_from_iban/i18n/nl.po
odoo/addons/base_bank_from_iban/models/__init__.py
odoo/addons/base_bank_from_iban/models/res_bank.py
odoo/addons/base_bank_from_iban/models/res_partner_bank.py
odoo/addons/base_bank_from_iban/readme/CONFIGURE.rst
odoo/addons/base_bank_from_iban/readme/CONTRIBUTORS.rst
odoo/addons/base_bank_from_iban/readme/DESCRIPTION.rst
odoo/addons/base_bank_from_iban/readme/USAGE.rst
odoo/addons/base_bank_from_iban/static/description/icon.png
odoo/addons/base_bank_from_iban/static/description/index.html
odoo/addons/base_bank_from_iban/tests/__init__.py
odoo/addons/base_bank_from_iban/tests/test_base_bank_from_iban.py
odoo/addons/base_bank_from_iban/views/res_bank_view.xml
odoo/addons/base_bank_from_iban/wizards/__init__.py
odoo/addons/base_bank_from_iban/wizards/account_setup_bank_manual_config.py
odoo14_addon_base_bank_from_iban-14.0.1.0.2.dist-info/METADATA
odoo14_addon_base_bank_from_iban-14.0.1.0.2.dist-info/WHEEL
odoo14_addon_base_bank_from_iban-14.0.1.0.2.dist-info/top_level.txt
odoo14_addon_base_bank_from_iban-14.0.1.0.2.dist-info/RECORD
